{
  "width": 25,
  "height": 25,
  "byteWidth": 100,
  "bitsPerPixel": 32,
  "bytesPerPixel": 4,
  "image": {
    "type": "Buffer",
    "data": [
      212,
      212,
      212,
      255,
      212,
      212,
      212,
      255,
      212,
      212,
      212,
      255,
      212,
      212,
      212,
      255,
      212,
      212,
      212,
      255,
      212,
      212,
      212,
      255,
      212,
      212,
      212,
      255,
      212,
      212,
      212,
      255,
      212,
      212,
      212,
      255,
      212,
      212,
      212,
      255,
      212,
      212,
      212,
      255,
      212,
      212,
      212,
      255,
      212,
      212,
      212,
      255,
      212,
      212,
      212,
      255,
      212,
      212,
      212,
      255,
      212,
      212,
      212,
      255,
      212,
      212,
      212,
      255,
      212,
      212,
      212,
      255,
      212,
      212,
      212,
      255,
      212,
      212,
      212,
      255,
      212,
      212,
      212,
      255,
      212,
      212,
      212,
      255,
      212,
      212,
      212,
      255,
      212,
      212,
      212,
      255,
      212,
      212,
      212,
      255,
      212,
      212,
      212,
      255,
      212,
      212,
      212,
      255,
      212,
      212,
      212,
      255,
      212,
      212,
      212,
      255,
      212,
      212,
      212,
      255,
      212,
      212,
      212,
      255,
      212,
      212,
      212,
      255,
      188,
      168,
      167,
      255,
      151,
      103,
      102,
      255,
      134,
      64,
      63,
      255,
      122,
      49,
      48,
      255,
      118,
      38,
      35,
      255,
      114,
      34,
      32,
      255,
      120,
      45,
      43,
      255,
      127,
      58,
      54,
      255,
      142,
      85,
      83,
      255,
      172,
      139,
      138,
      255,
      209,
      206,
      206,
      255,
      212,
      212,
      212,
      255,
      212,
      212,
      212,
      255,
      212,
      212,
      212,
      255,
      212,
      212,
      212,
      255,
      212,
      212,
      212,
      255,
      212,
      212,
      212,
      255,
      212,
      212,
      212,
      255,
      212,
      212,
      212,
      255,
      212,
      212,
      212,
      255,
      212,
      212,
      212,
      255,
      212,
      212,
      212,
      255,
      212,
      212,
      212,
      255,
      194,
      179,
      179,
      255,
      146,
      92,
      90,
      255,
      114,
      34,
      31,
      255,
      111,
      33,
      30,
      255,
      112,
      33,
      28,
      255,
      115,
      32,
      27,
      255,
      112,
      32,
      29,
      255,
      113,
      33,
      27,
      255,
      113,
      32,
      29,
      255,
      113,
      31,
      31,
      255,
      114,
      33,
      30,
      255,
      114,
      33,
      30,
      255,
      126,
      56,
      54,
      255,
      179,
      152,
      151,
      255,
      209,
      206,
      206,
      255,
      212,
      212,
      212,
      255,
      212,
      212,
      212,
      255,
      212,
      212,
      212,
      255,
      212,
      212,
      212,
      255,
      212,
      212,
      212,
      255,
      212,
      212,
      212,
      255,
      212,
      212,
      212,
      255,
      212,
      212,
      212,
      255,
      212,
      212,
      212,
      255,
      179,
      152,
      151,
      255,
      113,
      33,
      29,
      255,
      114,
      32,
      29,
      255,
      113,
      32,
      30,
      255,
      117,
      32,
      29,
      255,
      107,
      33,
      32,
      255,
      107,
      53,
      59,
      255,
      97,
      59,
      73,
      255,
      95,
      57,
      70,
      255,
      109,
      61,
      68,
      255,
      106,
      39,
      37,
      255,
      112,
      31,
      30,
      255,
      113,
      32,
      30,
      255,
      113,
      32,
      30,
      255,
      114,
      33,
      30,
      255,
      146,
      92,
      90,
      255,
      212,
      212,
      212,
      255,
      212,
      212,
      212,
      255,
      212,
      212,
      212,
      255,
      212,
      212,
      212,
      255,
      212,
      212,
      212,
      255,
      212,
      212,
      212,
      255,
      212,
      212,
      212,
      255,
      212,
      212,
      212,
      255,
      167,
      130,
      128,
      255,
      117,
      39,
      36,
      255,
      114,
      32,
      29,
      255,
      110,
      32,
      30,
      255,
      113,
      33,
      28,
      255,
      102,
      50,
      59,
      255,
      96,
      48,
      57,
      255,
      94,
      69,
      79,
      255,
      80,
      102,
      124,
      255,
      82,
      105,
      137,
      255,
      96,
      81,
      96,
      255,
      99,
      52,
      56,
      255,
      104,
      79,
      87,
      255,
      108,
      32,
      29,
      255,
      113,
      32,
      30,
      255,
      114,
      33,
      30,
      255,
      114,
      32,
      30,
      255,
      138,
      77,
      76,
      255,
      212,
      212,
      212,
      255,
      212,
      212,
      212,
      255,
      212,
      212,
      212,
      255,
      212,
      212,
      212,
      255,
      212,
      212,
      212,
      255,
      212,
      212,
      212,
      255,
      183,
      159,
      158,
      255,
      114,
      33,
      30,
      255,
      114,
      33,
      30,
      255,
      115,
      32,
      29,
      255,
      107,
      32,
      30,
      255,
      103,
      44,
      50,
      255,
      98,
      46,
      55,
      255,
      97,
      110,
      121,
      255,
      77,
      139,
      220,
      255,
      40,
      79,
      221,
      255,
      48,
      85,
      230,
      255,
      74,
      138,
      228,
      255,
      111,
      152,
      173,
      255,
      97,
      38,
      47,
      255,
      111,
      78,
      87,
      255,
      107,
      35,
      35,
      255,
      113,
      33,
      30,
      255,
      113,
      32,
      30,
      255,
      112,
      33,
      30,
      255,
      146,
      92,
      90,
      255,
      209,
      206,
      206,
      255,
      212,
      212,
      212,
      255,
      212,
      212,
      212,
      255,
      212,
      212,
      212,
      255,
      209,
      206,
      206,
      255,
      118,
      43,
      41,
      255,
      113,
      33,
      29,
      255,
      113,
      32,
      30,
      255,
      114,
      33,
      29,
      255,
      112,
      52,
      56,
      255,
      94,
      37,
      44,
      255,
      94,
      51,
      56,
      255,
      95,
      155,
      222,
      255,
      39,
      58,
      218,
      255,
      38,
      56,
      217,
      255,
      54,
      81,
      226,
      255,
      40,
      58,
      222,
      255,
      87,
      143,
      228,
      255,
      110,
      105,
      108,
      255,
      98,
      19,
      23,
      255,
      125,
      81,
      81,
      255,
      112,
      32,
      29,
      255,
      114,
      32,
      28,
      255,
      113,
      32,
      30,
      255,
      114,
      33,
      30,
      255,
      179,
      152,
      151,
      255,
      212,
      212,
      212,
      255,
      212,
      212,
      212,
      255,
      212,
      212,
      212,
      255,
      158,
      113,
      111,
      255,
      113,
      33,
      30,
      255,
      113,
      32,
      29,
      255,
      113,
      32,
      29,
      255,
      107,
      38,
      35,
      255,
      118,
      108,
      118,
      255,
      90,
      13,
      20,
      255,
      102,
      98,
      115,
      255,
      65,
      104,
      227,
      255,
      26,
      27,
      247,
      255,
      42,
      60,
      223,
      255,
      44,
      56,
      228,
      255,
      34,
      35,
      241,
      255,
      58,
      80,
      234,
      255,
      132,
      171,
      177,
      255,
      97,
      4,
      1,
      255,
      139,
      144,
      146,
      255,
      122,
      83,
      87,
      255,
      115,
      33,
      28,
      255,
      112,
      32,
      30,
      255,
      114,
      33,
      30,
      255,
      126,
      56,
      54,
      255,
      209,
      206,
      206,
      255,
      212,
      212,
      212,
      255,
      212,
      212,
      212,
      255,
      126,
      55,
      53,
      255,
      113,
      33,
      29,
      255,
      113,
      31,
      31,
      255,
      115,
      32,
      28,
      255,
      119,
      89,
      90,
      255,
      131,
      198,
      220,
      255,
      92,
      29,
      38,
      255,
      95,
      93,
      110,
      255,
      75,
      119,
      231,
      255,
      27,
      32,
      242,
      255,
      80,
      136,
      230,
      255,
      87,
      151,
      231,
      255,
      41,
      54,
      240,
      255,
      72,
      95,
      231,
      255,
      145,
      169,
      170,
      255,
      95,
      7,
      9,
      255,
      165,
      215,
      215,
      255,
      139,
      159,
      167,
      255,
      110,
      31,
      30,
      255,
      114,
      33,
      28,
      255,
      114,
      33,
      30,
      255,
      114,
      33,
      30,
      255,
      171,
      138,
      137,
      255,
      212,
      212,
      212,
      255,
      198,
      187,
      187,
      255,
      114,
      33,
      30,
      255,
      114,
      32,
      29,
      255,
      114,
      32,
      30,
      255,
      112,
      33,
      27,
      255,
      119,
      126,
      133,
      255,
      117,
      202,
      224,
      255,
      93,
      56,
      75,
      255,
      94,
      33,
      36,
      255,
      118,
      185,
      219,
      255,
      97,
      159,
      230,
      255,
      99,
      169,
      231,
      255,
      105,
      175,
      229,
      255,
      112,
      171,
      229,
      255,
      141,
      206,
      229,
      255,
      119,
      79,
      86,
      255,
      109,
      36,
      37,
      255,
      175,
      232,
      238,
      255,
      149,
      199,
      203,
      255,
      110,
      43,
      43,
      255,
      115,
      32,
      30,
      255,
      114,
      33,
      30,
      255,
      114,
      33,
      30,
      255,
      142,
      85,
      83,
      255,
      212,
      212,
      212,
      255,
      155,
      108,
      106,
      255,
      114,
      33,
      30,
      255,
      114,
      32,
      30,
      255,
      110,
      33,
      28,
      255,
      110,
      31,
      31,
      255,
      128,
      163,
      174,
      255,
      149,
      223,
      239,
      255,
      104,
      125,
      144,
      255,
      102,
      3,
      4,
      255,
      64,
      37,
      135,
      255,
      62,
      94,
      231,
      255,
      64,
      114,
      221,
      255,
      72,
      133,
      220,
      255,
      72,
      104,
      227,
      255,
      59,
      60,
      188,
      255,
      99,
      6,
      7,
      255,
      138,
      111,
      109,
      255,
      179,
      236,
      237,
      255,
      155,
      223,
      226,
      255,
      109,
      46,
      46,
      255,
      112,
      33,
      30,
      255,
      114,
      33,
      30,
      255,
      114,
      33,
      30,
      255,
      127,
      58,
      55,
      255,
      212,
      212,
      212,
      255,
      135,
      72,
      70,
      255,
      114,
      33,
      30,
      255,
      113,
      32,
      30,
      255,
      112,
      32,
      29,
      255,
      114,
      32,
      28,
      255,
      98,
      86,
      100,
      255,
      126,
      211,
      235,
      255,
      141,
      210,
      231,
      255,
      88,
      25,
      31,
      255,
      67,
      9,
      99,
      255,
      51,
      51,
      202,
      255,
      54,
      82,
      214,
      255,
      70,
      104,
      206,
      255,
      67,
      79,
      196,
      255,
      57,
      17,
      140,
      255,
      95,
      9,
      13,
      255,
      166,
      207,
      212,
      255,
      198,
      244,
      244,
      255,
      122,
      179,
      183,
      255,
      108,
      32,
      32,
      255,
      112,
      32,
      30,
      255,
      114,
      33,
      30,
      255,
      114,
      33,
      30,
      255,
      121,
      46,
      43,
      255,
      212,
      212,
      212,
      255,
      118,
      41,
      38,
      255,
      114,
      33,
      30,
      255,
      114,
      32,
      30,
      255,
      111,
      33,
      28,
      255,
      114,
      31,
      29,
      255,
      110,
      131,
      141,
      255,
      113,
      200,
      224,
      255,
      132,
      212,
      233,
      255,
      94,
      126,
      148,
      255,
      84,
      33,
      42,
      255,
      94,
      28,
      42,
      255,
      81,
      34,
      54,
      255,
      100,
      97,
      122,
      255,
      85,
      19,
      27,
      255,
      101,
      24,
      30,
      255,
      123,
      121,
      123,
      255,
      148,
      233,
      236,
      255,
      152,
      236,
      239,
      255,
      132,
      229,
      235,
      255,
      107,
      51,
      52,
      255,
      113,
      33,
      28,
      255,
      114,
      33,
      30,
      255,
      114,
      33,
      30,
      255,
      115,
      35,
      32,
      255,
      212,
      212,
      212,
      255,
      125,
      54,
      51,
      255,
      114,
      33,
      30,
      255,
      112,
      33,
      29,
      255,
      118,
      31,
      30,
      255,
      110,
      33,
      27,
      255,
      99,
      52,
      61,
      255,
      99,
      158,
      187,
      255,
      125,
      201,
      221,
      255,
      152,
      209,
      224,
      255,
      100,
      188,
      220,
      255,
      81,
      160,
      201,
      255,
      98,
      194,
      223,
      255,
      101,
      212,
      236,
      255,
      102,
      193,
      216,
      255,
      117,
      209,
      221,
      255,
      145,
      220,
      229,
      255,
      138,
      225,
      231,
      255,
      127,
      218,
      224,
      255,
      108,
      101,
      102,
      255,
      116,
      31,
      29,
      255,
      111,
      32,
      30,
      255,
      114,
      33,
      30,
      255,
      114,
      33,
      30,
      255,
      117,
      39,
      36,
      255,
      212,
      212,
      212,
      255,
      142,
      84,
      82,
      255,
      114,
      33,
      30,
      255,
      113,
      33,
      29,
      255,
      112,
      32,
      29,
      255,
      112,
      32,
      30,
      255,
      113,
      32,
      27,
      255,
      99,
      39,
      42,
      255,
      94,
      135,
      164,
      255,
      106,
      193,
      227,
      255,
      121,
      202,
      231,
      255,
      96,
      198,
      225,
      255,
      75,
      179,
      229,
      255,
      93,
      203,
      236,
      255,
      94,
      198,
      233,
      255,
      105,
      211,
      235,
      255,
      126,
      211,
      219,
      255,
      125,
      207,
      221,
      255,
      95,
      96,
      109,
      255,
      107,
      33,
      29,
      255,
      111,
      32,
      30,
      255,
      116,
      32,
      29,
      255,
      114,
      33,
      30,
      255,
      114,
      33,
      30,
      255,
      123,
      50,
      48,
      255,
      212,
      212,
      212,
      255,
      167,
      131,
      130,
      255,
      114,
      33,
      30,
      255,
      114,
      32,
      30,
      255,
      114,
      32,
      29,
      255,
      113,
      32,
      29,
      255,
      113,
      29,
      31,
      255,
      110,
      127,
      143,
      255,
      100,
      184,
      211,
      255,
      99,
      187,
      213,
      255,
      110,
      190,
      206,
      255,
      128,
      194,
      208,
      255,
      122,
      207,
      224,
      255,
      92,
      196,
      230,
      255,
      83,
      196,
      223,
      255,
      99,
      202,
      226,
      255,
      107,
      211,
      231,
      255,
      96,
      208,
      238,
      255,
      93,
      181,
      209,
      255,
      107,
      54,
      60,
      255,
      112,
      33,
      28,
      255,
      113,
      32,
      30,
      255,
      114,
      33,
      30,
      255,
      114,
      33,
      30,
      255,
      131,
      65,
      63,
      255,
      212,
      212,
      212,
      255,
      207,
      204,
      204,
      255,
      117,
      39,
      36,
      255,
      114,
      33,
      30,
      255,
      114,
      33,
      30,
      255,
      114,
      33,
      30,
      255,
      114,
      32,
      29,
      255,
      107,
      37,
      33,
      255,
      109,
      77,
      84,
      255,
      95,
      112,
      141,
      255,
      91,
      142,
      178,
      255,
      101,
      181,
      213,
      255,
      104,
      197,
      224,
      255,
      103,
      206,
      236,
      255,
      106,
      185,
      206,
      255,
      107,
      155,
      169,
      255,
      108,
      122,
      131,
      255,
      110,
      82,
      86,
      255,
      108,
      40,
      40,
      255,
      109,
      33,
      28,
      255,
      118,
      32,
      29,
      255,
      112,
      32,
      30,
      255,
      114,
      33,
      30,
      255,
      114,
      33,
      30,
      255,
      152,
      103,
      102,
      255,
      212,
      212,
      212,
      255,
      212,
      212,
      212,
      255,
      135,
      72,
      70,
      255,
      114,
      33,
      30,
      255,
      114,
      33,
      30,
      255,
      113,
      32,
      29,
      255,
      114,
      32,
      29,
      255,
      116,
      31,
      29,
      255,
      111,
      31,
      32,
      255,
      114,
      32,
      29,
      255,
      108,
      33,
      28,
      255,
      107,
      32,
      32,
      255,
      107,
      52,
      54,
      255,
      107,
      60,
      64,
      255,
      105,
      36,
      35,
      255,
      111,
      33,
      28,
      255,
      113,
      32,
      27,
      255,
      111,
      32,
      29,
      255,
      114,
      31,
      30,
      255,
      115,
      30,
      32,
      255,
      112,
      32,
      30,
      255,
      115,
      32,
      28,
      255,
      114,
      33,
      30,
      255,
      114,
      34,
      31,
      255,
      187,
      168,
      167,
      255,
      212,
      212,
      212,
      255,
      212,
      212,
      212,
      255,
      179,
      152,
      151,
      255,
      113,
      33,
      30,
      255,
      113,
      32,
      29,
      255,
      105,
      33,
      32,
      255,
      108,
      38,
      35,
      255,
      107,
      33,
      29,
      255,
      106,
      32,
      29,
      255,
      115,
      52,
      52,
      255,
      107,
      30,
      27,
      255,
      113,
      38,
      35,
      255,
      106,
      31,
      27,
      255,
      111,
      34,
      26,
      255,
      118,
      43,
      44,
      255,
      101,
      28,
      28,
      255,
      114,
      37,
      34,
      255,
      120,
      53,
      52,
      255,
      112,
      46,
      44,
      255,
      106,
      32,
      27,
      255,
      102,
      35,
      35,
      255,
      111,
      43,
      42,
      255,
      111,
      31,
      29,
      255,
      147,
      92,
      90,
      255,
      212,
      212,
      212,
      255,
      212,
      212,
      212,
      255,
      212,
      212,
      212,
      255,
      210,
      210,
      210,
      255,
      145,
      90,
      88,
      255,
      110,
      35,
      33,
      255,
      114,
      83,
      80,
      255,
      117,
      98,
      94,
      255,
      97,
      33,
      34,
      255,
      119,
      100,
      98,
      255,
      119,
      104,
      104,
      255,
      95,
      34,
      32,
      255,
      103,
      75,
      73,
      255,
      111,
      76,
      76,
      255,
      110,
      51,
      48,
      255,
      113,
      95,
      93,
      255,
      108,
      80,
      78,
      255,
      120,
      61,
      60,
      255,
      118,
      111,
      112,
      255,
      86,
      68,
      67,
      255,
      125,
      73,
      70,
      255,
      122,
      104,
      101,
      255,
      81,
      57,
      54,
      255,
      110,
      30,
      31,
      255,
      194,
      179,
      179,
      255,
      212,
      212,
      212,
      255,
      212,
      212,
      212,
      255,
      212,
      212,
      212,
      255,
      212,
      212,
      212,
      255,
      201,
      192,
      192,
      255,
      126,
      57,
      55,
      255,
      117,
      69,
      67,
      255,
      121,
      84,
      81,
      255,
      97,
      50,
      47,
      255,
      112,
      70,
      68,
      255,
      116,
      76,
      75,
      255,
      98,
      46,
      42,
      255,
      115,
      74,
      72,
      255,
      102,
      53,
      53,
      255,
      108,
      36,
      33,
      255,
      118,
      78,
      75,
      255,
      95,
      48,
      45,
      255,
      114,
      58,
      54,
      255,
      102,
      57,
      58,
      255,
      101,
      69,
      66,
      255,
      110,
      42,
      40,
      255,
      95,
      41,
      41,
      255,
      112,
      70,
      67,
      255,
      178,
      152,
      151,
      255,
      212,
      212,
      212,
      255,
      212,
      212,
      212,
      255,
      212,
      212,
      212,
      255,
      212,
      212,
      212,
      255,
      212,
      212,
      212,
      255,
      212,
      212,
      212,
      255,
      209,
      206,
      206,
      255,
      124,
      52,
      50,
      255,
      112,
      32,
      29,
      255,
      114,
      32,
      30,
      255,
      116,
      32,
      29,
      255,
      113,
      32,
      29,
      255,
      111,
      32,
      28,
      255,
      112,
      32,
      29,
      255,
      112,
      32,
      29,
      255,
      114,
      33,
      29,
      255,
      113,
      32,
      29,
      255,
      110,
      32,
      28,
      255,
      112,
      31,
      27,
      255,
      113,
      32,
      29,
      255,
      114,
      32,
      30,
      255,
      113,
      33,
      29,
      255,
      114,
      32,
      30,
      255,
      166,
      129,
      127,
      255,
      212,
      212,
      212,
      255,
      212,
      212,
      212,
      255,
      212,
      212,
      212,
      255,
      212,
      212,
      212,
      255,
      212,
      212,
      212,
      255,
      212,
      212,
      212,
      255,
      212,
      212,
      212,
      255,
      212,
      212,
      212,
      255,
      201,
      192,
      192,
      255,
      145,
      91,
      89,
      255,
      114,
      33,
      30,
      255,
      114,
      33,
      30,
      255,
      114,
      33,
      30,
      255,
      114,
      33,
      30,
      255,
      114,
      33,
      30,
      255,
      114,
      33,
      30,
      255,
      114,
      33,
      30,
      255,
      114,
      33,
      30,
      255,
      114,
      33,
      30,
      255,
      114,
      33,
      30,
      255,
      114,
      33,
      30,
      255,
      114,
      33,
      30,
      255,
      119,
      43,
      41,
      255,
      183,
      159,
      158,
      255,
      212,
      212,
      212,
      255,
      212,
      212,
      212,
      255,
      212,
      212,
      212,
      255,
      212,
      212,
      212,
      255,
      212,
      212,
      212,
      255,
      212,
      212,
      212,
      255,
      212,
      212,
      212,
      255,
      212,
      212,
      212,
      255,
      212,
      212,
      212,
      255,
      212,
      212,
      212,
      255,
      210,
      210,
      210,
      255,
      179,
      152,
      151,
      255,
      135,
      72,
      70,
      255,
      117,
      39,
      36,
      255,
      114,
      33,
      30,
      255,
      114,
      33,
      30,
      255,
      114,
      33,
      30,
      255,
      114,
      33,
      30,
      255,
      114,
      33,
      30,
      255,
      114,
      33,
      30,
      255,
      114,
      33,
      30,
      255,
      126,
      55,
      53,
      255,
      158,
      113,
      111,
      255,
      209,
      206,
      206,
      255,
      212,
      212,
      212,
      255,
      212,
      212,
      212,
      255,
      212,
      212,
      212,
      255,
      212,
      212,
      212,
      255,
      212,
      212,
      212,
      255,
      212,
      212,
      212,
      255,
      212,
      212,
      212,
      255,
      212,
      212,
      212,
      255,
      212,
      212,
      212,
      255,
      212,
      212,
      212,
      255,
      212,
      212,
      212,
      255,
      212,
      212,
      212,
      255,
      212,
      212,
      212,
      255,
      212,
      212,
      212,
      255,
      207,
      204,
      204,
      255,
      167,
      131,
      130,
      255,
      142,
      84,
      82,
      255,
      125,
      54,
      51,
      255,
      118,
      41,
      38,
      255,
      135,
      72,
      70,
      255,
      155,
      108,
      106,
      255,
      198,
      187,
      187,
      255,
      212,
      212,
      212,
      255,
      212,
      212,
      212,
      255,
      212,
      212,
      212,
      255,
      212,
      212,
      212,
      255,
      212,
      212,
      212,
      255,
      212,
      212,
      212,
      255,
      212,
      212,
      212,
      255,
      212,
      212,
      212,
      255,
      212,
      212,
      212,
      255
    ]
  }
}